apathetic_schema/__init__.py
apathetic_schema/check_schema_conformance.py
apathetic_schema/collect_msg.py
apathetic_schema/constants.py
apathetic_schema/flush_schema_aggregators.py
apathetic_schema/namespace.py
apathetic_schema/py.typed
apathetic_schema/types.py
apathetic_schema/validate_typed_dict.py
apathetic_schema/warn_keys_once.py
apathetic_schema-0.1.3.dist-info/METADATA
apathetic_schema-0.1.3.dist-info/WHEEL
apathetic_schema-0.1.3.dist-info/entry_points.txt
apathetic_schema-0.1.3.dist-info/licenses/LICENSE
apathetic_schema-0.1.3.dist-info/RECORD
